walletconstructor/__init__.py
walletconstructor/security/__init__.py
walletconstructor/security/config.py
walletconstructor/security/security.py
walletconstructor/wallet/__init__.py
walletconstructor/wallet/contract.py
walletconstructor/wallet/tokens.py
walletconstructor/wallet/tokenutils.py
walletconstructor/wallet/transactiontoken.py
walletconstructor/wallet/transactionwallet.py
walletconstructor/wallet/wallet.py
walletconstructor/wallet/walletutils.py
walletconstructor-0.1.0.dist-info/LICENSE
walletconstructor-0.1.0.dist-info/METADATA
walletconstructor-0.1.0.dist-info/WHEEL
walletconstructor-0.1.0.dist-info/entry_points.txt
walletconstructor-0.1.0.dist-info/top_level.txt
walletconstructor-0.1.0.dist-info/RECORD
